[
    {
        "ProjectID": "RswNoAOtMb",
        "ProjectName": "ProjectName1"
    },
    {
        "ProjectID": "HoWzTcUkij",
        "ProjectName": "ProjectName2"
    },
    {
        "ProjectID": "OdfpMslPhs",
        "ProjectName": "ProjectName3"
    },
    {
        "ProjectID": "RULyVxtzkM",
        "ProjectName": "ProjectName4"
    },
    {
        "ProjectID": "oponHMjGSZ",
        "ProjectName": "ProjectName5"
    },
    {
        "ProjectID": "jcAzzlCfKK",
        "ProjectName": "ProjectName6"
    },
    {
        "ProjectID": "AeGdnzXbMa",
        "ProjectName": "ProjectName7"
    },
    {
        "ProjectID": "sdjgnjjfSu",
        "ProjectName": "ProjectName8"
    },
    {
        "ProjectID": "NCnAMDOphE",
        "ProjectName": "ProjectName9"
    },
    {
        "ProjectID": "WSjFTtZCwN",
        "ProjectName": "ProjectName10"
    },
    {
        "ProjectID": "eBMZdyZZtG",
        "ProjectName": "ProjectName11"
    },
    {
        "ProjectID": "lTIzbrjrgW",
        "ProjectName": "ProjectName12"
    },
    {
        "ProjectID": "WgtEZPEZdr",
        "ProjectName": "ProjectName13"
    },
    {
        "ProjectID": "RBhteKNynK",
        "ProjectName": "ProjectName14"
    },
    {
        "ProjectID": "SFxOPftABg",
        "ProjectName": "ProjectName15"
    },
    {
        "ProjectID": "sRkpsxtFIf",
        "ProjectName": "ProjectName16"
    },
    {
        "ProjectID": "ocosGaDhtm",
        "ProjectName": "ProjectName17"
    },
    {
        "ProjectID": "agGIIesPHU",
        "ProjectName": "ProjectName18"
    },
    {
        "ProjectID": "MKrhTCeKZi",
        "ProjectName": "ProjectName19"
    },
    {
        "ProjectID": "gTxBNhnggc",
        "ProjectName": "ProjectName20"
    }
]